{
  "source": "feathers/feather_004_本地技能包迭代全览.md",
  "title": "🪶 第4片羽毛 · 本地技能包迭代全览",
  "tags": [
    "技能",
    "版本",
    "迭代",
    "更新日志"
  ],
  "atoms": [
    {
      "fact": "tags: [技能, 版本, 迭代, 更新日志]",
      "section": "content",
      "type": "summary"
    },
    {
      "fact": "created: 2026-05-07T21:00:00+08:00",
      "section": "content",
      "type": "summary"
    },
    {
      "fact": "- v1.0.0 初版：四大目录 + 神蕴索引 + 自动存盘",
      "section": "content",
      "type": "summary"
    },
    {
      "fact": "- v1.1.0 中文注释规则 + 用户偏好 + Obsidian 集成",
      "section": "content",
      "type": "summary"
    },
    {
      "fact": "- v1.2.0 全局行为规则：先搜羽毛，命中引用，未命中建议存",
      "section": "content",
      "type": "summary"
    }
  ],
  "atom_count": 5,
  "created": "2026-05-21T22:23:23.341230"
}